pd_flatten/__init__.py
pd_flatten/flatten.py
pd_flatten-0.1.2.dist-info/LICENSE
pd_flatten-0.1.2.dist-info/METADATA
pd_flatten-0.1.2.dist-info/WHEEL
pd_flatten-0.1.2.dist-info/RECORD
